SetupVariableTracker/SetupVariableTracker.py
SetupVariableTracker/__init__.py
setupvariabletracker-0.0.7.dist-info/licenses/LICENSE
setupvariabletracker-0.0.7.dist-info/METADATA
setupvariabletracker-0.0.7.dist-info/WHEEL
setupvariabletracker-0.0.7.dist-info/top_level.txt
setupvariabletracker-0.0.7.dist-info/RECORD
