Metadata-Version: 2.4
Name: SetupVariableTracker
Version: 0.0.7
Summary: Small library to track and log the declaration of new (setup) variables
Home-page: https://github.com/Aypac/SetupVariableTracker
Author: Rene Vollmer
Author-email: admin@aypac.de
Maintainer: Rene Vollmer
Maintainer-email: admin@aypac.de
Classifier: Development Status :: 3 - Alpha
Classifier: Intended Audience :: Developers
Classifier: Topic :: Scientific/Engineering
Provides: SetupVariableTracker
Requires-Python: >=3.6
License-File: LICENSE
Requires-Dist: tabulate
Dynamic: author
Dynamic: author-email
Dynamic: classifier
Dynamic: description
Dynamic: description-content-type
Dynamic: home-page
Dynamic: license-file
Dynamic: maintainer
Dynamic: maintainer-email
Dynamic: provides
Dynamic: requires-dist
Dynamic: requires-python
Dynamic: summary
